eximhandler/__init__.py
eximhandler/eximhandler.py
EximHandler-1.1.0.dist-info/LICENSE
EximHandler-1.1.0.dist-info/METADATA
EximHandler-1.1.0.dist-info/WHEEL
EximHandler-1.1.0.dist-info/top_level.txt
EximHandler-1.1.0.dist-info/RECORD
