Metadata-Version: 2.1
Name: EximHandler
Version: 1.1.0
Summary: A logging handler class which sends an email using exim
Home-page: https://github.com/danmichaelo/eximhandler
Author: Dan Michael O. Heggø
Author-email: danmichaelo@gmail.com
License: UNKNOWN
Platform: UNKNOWN
Classifier: Programming Language :: Python :: 3
Classifier: License :: OSI Approved :: MIT License
